lytspel/__init__.py
lytspel/conv.py
lytspel/dict.py
lytspel/lytspel-dict.csv
lytspel/test.py
lytspel/util.py
lytspel/web.py
lytspel-2.1.3.dist-info/licenses/LICENSE.txt
lytspel-2.1.3.dist-info/METADATA
lytspel-2.1.3.dist-info/WHEEL
lytspel-2.1.3.dist-info/entry_points.txt
lytspel-2.1.3.dist-info/top_level.txt
lytspel-2.1.3.dist-info/RECORD
