Metadata-Version: 2.4
Name: lytspel
Version: 2.1.3
Summary: A Simple Phonetic Respelling for the English Language
Home-page: https://www.lytspel.org/
Author: Christian Siefkes
Author-email: christian@siefkes.net
License: ISC
Project-URL: Source, https://github.com/ChristianSi/lytspel
Project-URL: Tracker, https://github.com/ChristianSi/lytspel/issues
Keywords: english spelling reform lytspel
Classifier: Development Status :: 5 - Production/Stable
Classifier: License :: OSI Approved :: ISC License (ISCL)
Classifier: Natural Language :: English
Classifier: Operating System :: OS Independent
Classifier: Programming Language :: Python :: 3
Classifier: Topic :: Communications
Classifier: Topic :: Text Processing :: Linguistic
Requires-Python: >=3.9
License-File: LICENSE.txt
Requires-Dist: lxml>=4.0.0
Requires-Dist: setuptools>=34.3.3
Requires-Dist: spacy>=2.0.0
Dynamic: author
Dynamic: author-email
Dynamic: classifier
Dynamic: description
Dynamic: description-content-type
Dynamic: home-page
Dynamic: keywords
Dynamic: license
Dynamic: license-file
Dynamic: project-url
Dynamic: requires-dist
Dynamic: requires-python
Dynamic: summary
